Metadata-Version: 2.1
Name: numcu
Version: 1.0.5
Summary: Numerical CUDA-based Python library built on CuVec
Home-page: https://github.com/AMYPAD/NumCu
Author: Casper da Costa-Luis
Author-email: casper.dcl@physics.org
License: MPL-2.0
Project-URL: Changelog, https://github.com/AMYPAD/NumCu/releases
Project-URL: Documentation, https://amypad.github.io/NumCu
Keywords: Python,C,C++,buffer,vector,array,CUDA,CPython,SWIG,extensions,API
Classifier: Development Status :: 5 - Production/Stable
Classifier: Intended Audience :: Developers
Classifier: Environment :: GPU
Classifier: Environment :: GPU :: NVIDIA CUDA
Classifier: Intended Audience :: Education
Classifier: Intended Audience :: Science/Research
Classifier: License :: OSI Approved :: Mozilla Public License 2.0 (MPL 2.0)
Classifier: Operating System :: Microsoft :: Windows
Classifier: Operating System :: POSIX :: Linux
Classifier: Programming Language :: C
Classifier: Programming Language :: C++
Classifier: Programming Language :: Python :: 3
Classifier: Programming Language :: Python :: 3.7
Classifier: Programming Language :: Python :: 3.8
Classifier: Programming Language :: Python :: 3.9
Classifier: Programming Language :: Python :: 3.10
Classifier: Programming Language :: Python :: 3.11
Classifier: Programming Language :: Python :: 3 :: Only
Classifier: Topic :: Software Development :: Libraries
Classifier: Topic :: Software Development :: Libraries :: Python Modules
Classifier: Topic :: Utilities
Requires-Python: >=3.7
Provides-Extra: dev
License-File: LICENCE
